skfdiff/__init__.py
skfdiff/_version.py
skfdiff/model.py
skfdiff/simulation.py
skfdiff/utils.py
skfdiff/core/__init__.py
skfdiff/core/grid_builder.py
skfdiff/core/spatial_schemes.py
skfdiff/core/system.py
skfdiff/core/temporal_schemes.py
skfdiff/core/variables.py
skfdiff/core/backends/__init__.py
skfdiff/core/backends/base_backend.py
skfdiff/core/backends/numba_backend.py
skfdiff/core/backends/numpy_backend.py
skfdiff/plugins/__init__.py
skfdiff/plugins/container.py
skfdiff/plugins/displays.py
scikit_fdiff-0.7.0.dist-info/LICENSE
scikit_fdiff-0.7.0.dist-info/METADATA
scikit_fdiff-0.7.0.dist-info/WHEEL
scikit_fdiff-0.7.0.dist-info/top_level.txt
scikit_fdiff-0.7.0.dist-info/RECORD
