Metadata-Version: 2.1
Name: scikit-fdiff
Version: 0.7.0
Summary: Automatic finite difference discretization for 1D PDE with fast temporal solvers.
Home-page: https://gitlab.com/celliern/scikit-fdiff/
Author: N. Cellier
Author-email: contact@nicolas-cellier.net
License: MIT
Keywords: PDE,finite-difference,physic,modelling,interactive
Platform: UNKNOWN
Classifier: Programming Language :: Python :: 3
Classifier: Programming Language :: Python :: 3.7
Classifier: Programming Language :: Python :: 3.8
Classifier: Programming Language :: Python :: 3.9
Requires-Python: >=3.6
Requires-Dist: numpy
Requires-Dist: scipy
Requires-Dist: sympy (<1.6)
Requires-Dist: streamz
Requires-Dist: more-itertools
Requires-Dist: xarray
Requires-Dist: dask
Requires-Dist: pyyaml
Requires-Dist: joblib
Requires-Dist: path.py
Requires-Dist: tqdm
Requires-Dist: cloudpickle
Requires-Dist: attrs
Requires-Dist: matplotlib
Requires-Dist: holoviews
Requires-Dist: boltons
Requires-Dist: appdirs
Requires-Dist: python-forge
Requires-Dist: fuzzywuzzy
Requires-Dist: cachetools
Requires-Dist: cached-property
Requires-Dist: loguru
Provides-Extra: dev
Requires-Dist: pytest ; extra == 'dev'
Requires-Dist: pylama ; extra == 'dev'
Requires-Dist: pylint ; extra == 'dev'
Requires-Dist: pre-commit ; extra == 'dev'
Requires-Dist: pytest-coverage ; extra == 'dev'
Requires-Dist: pytest-xdist ; extra == 'dev'
Requires-Dist: versioneer ; extra == 'dev'
Provides-Extra: docs
Requires-Dist: sphinx ; extra == 'docs'
Requires-Dist: sphinx-rtd-theme ; extra == 'docs'
Requires-Dist: sphinx-gallery ; extra == 'docs'
Requires-Dist: nb2plots ; extra == 'docs'
Requires-Dist: doc8 ; extra == 'docs'
Requires-Dist: seaborn ; extra == 'docs'
Provides-Extra: interactive
Requires-Dist: ipython ; extra == 'interactive'
Requires-Dist: holoviews ; extra == 'interactive'
Requires-Dist: jupyter ; extra == 'interactive'
Requires-Dist: bokeh ; extra == 'interactive'
Requires-Dist: ipywidgets ; extra == 'interactive'
Provides-Extra: numba
Requires-Dist: numba ; extra == 'numba'
Requires-Dist: jinja2 ; extra == 'numba'
